copper/__init__.py
copper/delegate.py
copper/i2c/__init__.py
copper/i2c/htu21d.py
copper/i2c/pca9685.py
copper/spi/__init__.py
copper/usb/__init__.py
copper/usb/firmata.py
copper/usb/ftdi.py
copper/usb/tigertail.py
tests/i2c/__init__.py
tests/i2c/htu21d_test.py
tests/i2c/pca9685_test.py
copper-0.9.1.dist-info/LICENSE
copper-0.9.1.dist-info/METADATA
copper-0.9.1.dist-info/WHEEL
copper-0.9.1.dist-info/top_level.txt
copper-0.9.1.dist-info/RECORD
