Metadata-Version: 2.1
Name: copper
Version: 0.9.1
Summary: Module for interacting with electromechanical systems.
Home-page: https://github.com/google/copper
Author: UNKNOWN
Author-email: UNKNOWN
License: Apache 2 license
Platform: Linux
Platform: Darwin
Classifier: Development Status :: 5 - Production/Stable
Classifier: Framework :: Robot Framework :: Library
Classifier: Intended Audience :: Developers
Classifier: Intended Audience :: Manufacturing
Classifier: Intended Audience :: Science/Research
Classifier: Intended Audience :: Telecommunications Industry
Classifier: License :: OSI Approved :: Apache Software License
Classifier: Operating System :: MacOS :: MacOS X
Classifier: Operating System :: POSIX :: Linux
Classifier: Programming Language :: Python
Classifier: Programming Language :: Python :: 2.6
Classifier: Programming Language :: Python :: 2.7
Classifier: Programming Language :: Python :: 3.4
Classifier: Programming Language :: Python :: 3.5
Classifier: Topic :: Software Development
Classifier: Topic :: Software Development :: Embedded Systems
Classifier: Topic :: Software Development :: Libraries :: Python Modules
Classifier: Topic :: Software Development :: Testing
Classifier: Topic :: System :: Hardware :: Hardware Drivers
Requires-Dist: pyfirmata
Requires-Dist: pylibftdi
Requires-Dist: pyusb
Requires-Dist: usbinfo (>=1.1)
